{
  "users": [
    {
      "name": "Michael Chen",
      "avatar": "/profile.png",
      "level": 25,
      "xp": 2450,
      "badges": ["win", "streak"],
      "isYou": false
    },
    {
      "name": "Rafiananta",
      "avatar": "/profile.png",
      "level": 12,
      "xp": 1350,
      "badges": ["win", "streak"],
      "isYou": true
    },
    {
      "name": "David Kim",
      "avatar": "/profile.png",
      "level": 11,
      "xp": 1290,
      "badges": ["streak", "speed"],
      "isYou": false
    },
    {
      "name": "Emma Wilson",
      "avatar": "/profile.png",
      "level": 10,
      "xp": 1180,
      "badges": ["perfect"],
      "isYou": false
    },
    {
      "name": "David Kim",
      "avatar": "/profile.png",
      "level": 11,
      "xp": 1290,
      "badges": ["streak", "speed"],
      "isYou": false
    },
    {
      "name": "Emma Wilson",
      "avatar": "/profile.png",
      "level": 10,
      "xp": 1180,
      "badges": ["perfect"],
      "isYou": false
    },
    {
      "name": "David Kim",
      "avatar": "/profile.png",
      "level": 11,
      "xp": 1290,
      "badges": ["streak", "speed"],
      "isYou": false
    },
    {
      "name": "Emma Wilson",
      "avatar": "/profile.png",
      "level": 10,
      "xp": 1180,
      "badges": ["perfect"],
      "isYou": false
    }
  ]
}